{
  "none": {
    "name": "无套路",
    "architect": "不强制套用固定套路，优先服从用户创意与人物自身因果。",
    "writer": "自然推进本章冲突，不为套公式强行制造误会、反转或打脸。",
    "auditor": "仅检查故事自身逻辑，不以固定套路完整度作为硬伤。"
  },
  "wife_chasing": {
    "name": "追妻火葬场",
    "architect": "前段建立伤害与失望，中段完成关系决裂和女主成长，后段让追悔与补偿付出真实代价；复合与否必须由人物选择和行动决定。",
    "writer": "用具体行动呈现关系失衡、失望累积和追悔代价，禁止只靠旁白宣布后悔或轻易原谅。",
    "auditor": "检查伤害、决裂、追悔、补偿之间是否有充分因果；缺少铺垫属于警告，人物行为前后矛盾才属于硬伤。"
  },
  "rule_horror": {
    "name": "规则怪谈",
    "architect": "建立可验证的规则、违规代价、真假规则和逐步揭示的底层机制；每章至少推进一次规则认知或生存选择。",
    "writer": "规则必须通过事件被验证或质疑，恐惧来自选择代价和信息差，避免无理由惊吓与随意改规则。",
    "auditor": "检查规则、违规后果和已揭示机制是否自洽；明确违反既有规则且无解释属于硬伤。"
  },
  "counterattack": {
    "name": "逆袭打脸",
    "architect": "按受压、蓄力、证据或能力积累、公开反转、余波升级组织节奏，打脸必须带来新的局势变化。",
    "writer": "先建立对手确信会赢的依据，再用主角准备和行动完成反转，避免凭空降智或无成本碾压。",
    "auditor": "检查反转所需能力、证据和机会是否提前成立；凭空获得关键条件属于硬伤。"
  },
  "marriage_first": {
    "name": "先婚后爱",
    "architect": "先明确婚姻契约与利益边界，再通过共同事件积累信任、暴露脆弱和改变关系，感情转折必须有可见过程。",
    "writer": "用共同选择、边界试探和行动回应推进感情，避免突然心动和重复误会拖延。",
    "auditor": "检查关系变化是否有事件支撑；轻微铺垫不足属于警告，违背已确认关系边界且无解释属于硬伤。"
  },
  "infinite_trials": {
    "name": "无限流闯关",
    "architect": "每个关卡明确目标、限制、失败代价、线索链和通关逻辑，同时推进队伍关系与主线谜团。",
    "writer": "线索必须可追溯，解法来自已出现的信息与人物能力，关卡危险不能临时取消。",
    "auditor": "检查目标、规则、线索、解法和代价是否闭环；无依据解题或规则临时失效属于硬伤。"
  },
  "revenge_rebirth": {
    "name": "复仇重生",
    "architect": "明确前世失败原因、今生信息优势、复仇对象层级与代价，让每次改命产生新的连锁反应。",
    "writer": "主角只能利用其合理掌握的前世信息，复仇推进要有筹备、风险和后果，避免全知全能。",
    "auditor": "检查主角是否知道不可能知道的信息、改命后世界是否仍机械复刻前世；明显信息越界属于硬伤。"
  },
  "female_angst_awakening": {
    "name": "女频虐恋觉醒",
    "strong": true,
    "core_driver": "relationship_angst_awakening",
    "world_policy": "allow_all",
    "forbidden_material_drivers": [
      "male_power_fantasy",
      "rule_horror_survival",
      "horror_survival"
    ],
    "background_only_drivers": [
      "world_stage"
    ],
    "material_note": "世界观题材默认可套用；随机素材只能作为舞台、人物关系或局部冲突补充，不能替代“伤害-心死-觉醒-追悔”的主线驱动力。",
    "architect": "严格执行已确认的套路契约与逐章节拍计划。女主必须沿着隐忍、心死、平静离开的路径成长；男主必须晚于伤害发生后才逐步察觉真相，并为偏信与伤害承担长期代价。",
    "writer": "使用对比、信息差和具体场景呈现伤害。女主前期可以痛苦隐忍，后期必须越来越平静坚定，禁止重复哭闹解释；男主追悔必须落实为行动和损失。",
    "auditor": "逐项检查当前章节的套路任务、女主情绪状态、男主认知状态和关系变化。缺失当前章节必须完成的事件属于套路执行失败；情绪浓度略弱只列为警告。",
    "compatible_styles": ["default", "literary", "cold"],
    "ending_options": {
      "no_reunion": "女主彻底离开并拥有更好生活，男主追悔但无法挽回。",
      "costly_reunion": "男主付出长期且不可逆的代价后，女主自主决定是否重新开始。"
    },
    "heroine_pool": [
      "孤儿出身，被男主家庭视作外人，善良隐忍但最终觉醒",
      "被抱错的真千金，回家后长期被忽视，后期平静收回人生",
      "乡下长大的女孩，因出身被轻视，最终建立独立事业与边界",
      "被原生家庭忽视的女儿，习惯讨好所有人，最终停止解释和牺牲"
    ],
    "hero_pool": [
      "豪门继承人，对女配偏信，对女主冷漠并用资源实施情绪惩罚",
      "权势精英，习惯掌控关系，把女主的隐忍误判为离不开自己",
      "高社会地位的青梅竹马，公开维护女配，直到失去女主才察觉真相"
    ],
    "rival_pool": [
      "白莲花前女友，擅长示弱并把责任推给女主",
      "绿茶养妹，利用家人偏爱制造女主有错的假象",
      "表面亲密的闺蜜，借女主信任接近男主并反咬一口",
      "小青梅女配，用共同回忆和脆弱姿态让男主持续偏袒"
    ],
    "background_pool": ["豪门婚恋", "娱乐圈", "校园青梅", "都市家庭"],
    "conflict_modules": [
      {"id": "public_humiliation", "name": "公开羞辱", "category": "social", "description": "男主或其圈层在公开场合贬低女主，女配从中获利。"},
      {"id": "favor_rival", "name": "偏袒女配", "category": "relationship", "description": "每次女主与女配冲突，男主先入为主维护女配。"},
      {"id": "framed_blame", "name": "诬陷背锅", "category": "plot", "description": "女配制造证据让女主承担错误或恶意行为。"},
      {"id": "family_cold_violence", "name": "家庭冷暴力", "category": "relationship", "description": "家庭成员集体忽视或惩罚女主，让她逐步停止期待。"},
      {"id": "hidden_illness", "name": "隐瞒伤病", "category": "information_gap", "description": "女主独自承受严重伤病，男主因信息差继续误解她。"},
      {"id": "hidden_pregnancy", "name": "隐瞒怀孕", "category": "reproductive", "description": "女主因失望或风险隐瞒怀孕，男主直到伤害后才得知。"},
      {"id": "pregnancy_loss", "name": "流产或孩子伤害", "category": "reproductive", "description": "严重伤害导致孩子受损，必须建立充分因果且不得作为廉价刺激。"},
      {"id": "critical_abandonment", "name": "关键时刻抛弃", "category": "plot", "description": "女主最需要帮助时，男主因偏信女配选择离开。"}
    ],
    "beats": [
      {"id": "hook", "range": "前300字", "requirement": "女主立即遭受伤害、羞辱或被抛弃，核心冲突爆发。"},
      {"id": "accumulation", "range": "0%-25%", "requirement": "虐点叠加，女主隐忍并开始察觉异常，男主持续偏袒女配。"},
      {"id": "escalation", "range": "25%-45%", "requirement": "伤害升级并触发关键事件，女主由痛苦转为心死。"},
      {"id": "paywall_turn", "range": "45%-50%", "requirement": "发生最严重伤害与反转钩子，男主首次察觉事情不对。"},
      {"id": "truth_regret", "range": "50%-80%", "requirement": "真相逐步揭露，男主追悔补偿，女主拒绝解释和回头。"},
      {"id": "independent_ending", "range": "80%-100%", "requirement": "女主独立并进入更好生活，男主承担长期后果。"}
    ],
    "writing_techniques": [
      "对比手法：女主受伤时，女配正在获得幸福、关注或利益。",
      "信息差：男主不知道女主真实伤痛、怀孕或过往经历。",
      "反转设计：女主停止解释后，证据与真相自然揭开，男主才发现自己错得彻底。",
      "画面感：关键场景使用具体空间、动作和视觉焦点，避免旁白直接宣布情绪。",
      "平静伤人：女主越往后越平静，读者越能感到她已经彻底失望。"
    ],
    "audit_rules": [
      "缺失当前章节计划中的必须事件、人物状态或关系变化时，列入套路问题并判定不通过。",
      "女主在心死阶段之后重新反复哭闹、解释或无代价回头时，列入套路问题。",
      "男主提前知道女主真实伤痛却仍被写成信息差时，列入逻辑硬伤。",
      "情绪浓度略弱、对比不够鲜明或画面感不足只列入警告，不触发退稿。",
      "套路问题与逻辑硬伤分别记录，不得用套路偏好冒充逻辑错误。"
    ],
    "forbidden": [
      "禁止所有虐点无因果地同时出现。",
      "禁止男主一句道歉就获得原谅。",
      "禁止女主后期反复哭闹、解释或主动求复合。",
      "禁止女配和男主为推动剧情突然降智。",
      "禁止默认结局中女主因怀孕、家人或舆论压力回头。"
    ]
  },
  "custom": {
    "name": "自定义套路",
    "architect": "严格提炼并执行用户提供的自定义套路要求，同时保证人物因果自然。",
    "writer": "执行自定义套路要求，但不得为了套用套路破坏既有设定和人物动机。",
    "auditor": "检查自定义套路推进是否与世界观、连续性和人物动机冲突。"
  }
}
